{
  "meta": {
    "source": "https://zs.scu.edu.cn",
    "updated": "2026-06-17",
    "target_cohort": "2026年高考"
  },
  "policies": [
    {
      "title": "2026年普通本科招生章程",
      "summary": "最新发布。含录取规则、同分排序、专业调剂、体检要求等，26届填报必读。",
      "url": "https://zs.scu.edu.cn/zsxx/zszc/bkzs/",
      "category": "招生章程",
      "year": 2026,
      "featured": true
    },
    {
      "title": "2026年强基计划招生简章",
      "summary": "数学、物理、化学、生物、基础医学等基础学科，4月报名、6月校测。",
      "url": "https://zs.scu.edu.cn/zsxx/zszc/bkzs/202604/t20260410_136892.html",
      "category": "强基计划",
      "year": 2026,
      "featured": true
    },
    {
      "title": "2026年艺术类本科招生简章",
      "summary": "美术、音乐、舞蹈等艺术类专业报名条件与考试安排。",
      "url": "https://zs.scu.edu.cn/zsxx/zszc/bkzs/202604/t20260418_136978.html",
      "category": "艺术类",
      "year": 2026,
      "featured": false
    },
    {
      "title": "2026年运动训练专业招生简章",
      "summary": "体育单招运动训练专业报名与录取说明。",
      "url": "https://zs.scu.edu.cn/zsxx/zszc/bkzs/202503/t20250320_136654.html",
      "category": "体育类",
      "year": 2026,
      "featured": false
    },
    {
      "title": "2025年国家专项计划招生简章",
      "summary": "面向农村和脱贫地区学生，2026年细则以当年公布为准。",
      "url": "https://zs.scu.edu.cn/zsxx/zszc/bkzs/202504/t20250415_136945.html",
      "category": "专项计划",
      "year": 2025,
      "featured": true
    },
    {
      "title": "2025年高校专项计划招生简章",
      "summary": "2026年高校专项不提前报名，投档须达省特控线。",
      "url": "https://zs.scu.edu.cn/zsxx/zszc/bkzs/202504/t20250415_136946.html",
      "category": "专项计划",
      "year": 2025,
      "featured": false
    },
    {
      "title": "四川大学匹兹堡学院招生",
      "summary": "中外合作办学，全英文教学，独立代码。",
      "url": "https://scupi.scu.edu.cn/admissions",
      "category": "中外合作",
      "year": 2026,
      "featured": true
    },
    {
      "title": "中德合作办学电气工程及其自动化",
      "summary": "与德国克劳斯塔尔工业大学合作办学。",
      "url": "https://zs.scu.edu.cn/zsxx/zszc/bkzs/202504/t20250422_137012.html",
      "category": "中外合作",
      "year": 2025,
      "featured": false
    },
    {
      "title": "2026年分省招生计划",
      "summary": "官方分省分专业招生人数查询。",
      "url": "https://zs.scu.edu.cn/zsxx/zsjh/",
      "category": "招生计划",
      "year": 2026,
      "featured": true
    },
    {
      "title": "历年录取分数线（官方）",
      "summary": "各省各批次录取分数与位次，建议与本站数据交叉核对。",
      "url": "https://zs.scu.edu.cn/zsxx/lqfs/",
      "category": "录取分数",
      "year": 2026,
      "featured": true
    },
    {
      "title": "本科招生专业目录",
      "summary": "川大全部本科招生专业及学院一览。",
      "url": "https://zs.scu.edu.cn/zsxx/zyjs/",
      "category": "专业介绍",
      "year": 2026,
      "featured": false
    },
    {
      "title": "阳光高考平台 · 川大章程",
      "summary": "教育部阳光高考备案招生章程。",
      "url": "https://gaokao.chsi.com.cn/zsgs/zhangcheng/listVerifYz--method=index,lb=1",
      "category": "招生章程",
      "year": 2026,
      "featured": false
    },
    {
      "title": "新生入学须知",
      "summary": "报到、住宿、军训等迎新信息。",
      "url": "https://yx.scu.edu.cn/",
      "category": "校园生活",
      "year": 2026,
      "featured": false
    },
    {
      "title": "学生资助政策",
      "summary": "奖学金、助学金、助学贷款。",
      "url": "https://xszz.scu.edu.cn/",
      "category": "奖助学金",
      "year": 2026,
      "featured": false
    },
    {
      "title": "常见问题解答",
      "summary": "志愿填报、录取、报到高频问题。",
      "url": "https://zs.scu.edu.cn/zsxx/cjwt/",
      "category": "常见问题",
      "year": 2026,
      "featured": false
    }
  ]
}
